sagellm_protocol/__init__.py
sagellm_protocol/__init__.pyc
sagellm_protocol/backend_types.pyc
sagellm_protocol/errors.pyc
sagellm_protocol/kv_hooks.pyc
sagellm_protocol/openai_types.pyc
sagellm_protocol/py.typed
sagellm_protocol/sampling.pyc
sagellm_protocol/timestamps.pyc
sagellm_protocol/types.pyc
sagellm_protocol/__pycache__/__init__.cpython-311.pyc
sagellm_protocol/__pycache__/backend_types.cpython-311.pyc
sagellm_protocol/__pycache__/errors.cpython-311.pyc
sagellm_protocol/__pycache__/kv_hooks.cpython-311.pyc
sagellm_protocol/__pycache__/openai_types.cpython-311.pyc
sagellm_protocol/__pycache__/sampling.cpython-311.pyc
sagellm_protocol/__pycache__/timestamps.cpython-311.pyc
sagellm_protocol/__pycache__/types.cpython-311.pyc
sagellm_protocol/kv/__init__.py
sagellm_protocol/kv/__init__.pyc
sagellm_protocol/kv/enums.pyc
sagellm_protocol/kv/errors.pyc
sagellm_protocol/kv/metrics.pyc
sagellm_protocol/kv/types.pyc
sagellm_protocol/kv/__pycache__/__init__.cpython-311.pyc
sagellm_protocol/kv/__pycache__/enums.cpython-311.pyc
sagellm_protocol/kv/__pycache__/errors.cpython-311.pyc
sagellm_protocol/kv/__pycache__/metrics.cpython-311.pyc
sagellm_protocol/kv/__pycache__/types.cpython-311.pyc
isagellm_protocol-0.4.0.8.dist-info/METADATA
isagellm_protocol-0.4.0.8.dist-info/WHEEL
isagellm_protocol-0.4.0.8.dist-info/top_level.txt
isagellm_protocol-0.4.0.8.dist-info/RECORD
